itkwasm_image_io_emscripten/__init__.py
itkwasm_image_io_emscripten/_version.py
itkwasm_image_io_emscripten/bio_rad_read_image_async.py
itkwasm_image_io_emscripten/bio_rad_write_image_async.py
itkwasm_image_io_emscripten/bmp_read_image_async.py
itkwasm_image_io_emscripten/bmp_write_image_async.py
itkwasm_image_io_emscripten/extension_to_image_io.py
itkwasm_image_io_emscripten/fdf_read_image_async.py
itkwasm_image_io_emscripten/fdf_write_image_async.py
itkwasm_image_io_emscripten/gdcm_read_image_async.py
itkwasm_image_io_emscripten/gdcm_write_image_async.py
itkwasm_image_io_emscripten/ge4_read_image_async.py
itkwasm_image_io_emscripten/ge4_write_image_async.py
itkwasm_image_io_emscripten/ge5_read_image_async.py
itkwasm_image_io_emscripten/ge5_write_image_async.py
itkwasm_image_io_emscripten/ge_adw_read_image_async.py
itkwasm_image_io_emscripten/ge_adw_write_image_async.py
itkwasm_image_io_emscripten/gipl_read_image_async.py
itkwasm_image_io_emscripten/gipl_write_image_async.py
itkwasm_image_io_emscripten/image_io_index.py
itkwasm_image_io_emscripten/jpeg_read_image_async.py
itkwasm_image_io_emscripten/jpeg_write_image_async.py
itkwasm_image_io_emscripten/js_package.py
itkwasm_image_io_emscripten/lsm_read_image_async.py
itkwasm_image_io_emscripten/lsm_write_image_async.py
itkwasm_image_io_emscripten/meta_read_image_async.py
itkwasm_image_io_emscripten/meta_write_image_async.py
itkwasm_image_io_emscripten/mgh_read_image_async.py
itkwasm_image_io_emscripten/mgh_write_image_async.py
itkwasm_image_io_emscripten/mrc_read_image_async.py
itkwasm_image_io_emscripten/mrc_write_image_async.py
itkwasm_image_io_emscripten/nifti_read_image_async.py
itkwasm_image_io_emscripten/nifti_write_image_async.py
itkwasm_image_io_emscripten/nrrd_read_image_async.py
itkwasm_image_io_emscripten/nrrd_write_image_async.py
itkwasm_image_io_emscripten/png_read_image_async.py
itkwasm_image_io_emscripten/png_write_image_async.py
itkwasm_image_io_emscripten/read_image_async.py
itkwasm_image_io_emscripten-1.6.0.dist-info/METADATA
itkwasm_image_io_emscripten-1.6.0.dist-info/WHEEL
itkwasm_image_io_emscripten-1.6.0.dist-info/RECORD
